{
  "project_info": {
    "project_number": "610941252952",
    "project_id": "wellness-buddy-5de14",
    "storage_bucket": "wellness-buddy-5de14.firebasestorage.app"
  },
  "client": [
    {
      "client_info": {
        "mobilesdk_app_id": "1:610941252952:android:a04c921f5a95815857e12d",
        "android_client_info": {
          "package_name": "com.wellnessbuddy.app"
        }
      },
      "oauth_client": [
        {
          "client_id": "610941252952-m9hukk2fkn8e3p4kf8kq12gcm2iv4qoh.apps.googleusercontent.com",
          "client_type": 1,
          "android_info": {
            "package_name": "com.wellnessbuddy.app",
            "certificate_hash": "28d018a391cb5ea3f6134da460dcbd285b6503e5"
          }
        },
        {
          "client_id": "610941252952-u9h8srgfr879aucl4sbc8h3f6i68cq7n.apps.googleusercontent.com",
          "client_type": 3
        }
      ],
      "api_key": [
        {
          "current_key": "AIzaSyArJQHNTFraEOp3ENdd67T6aV49hCCxoUo"
        }
      ],
      "services": {
        "appinvite_service": {
          "other_platform_oauth_client": [
            {
              "client_id": "610941252952-u9h8srgfr879aucl4sbc8h3f6i68cq7n.apps.googleusercontent.com",
              "client_type": 3
            }
          ]
        }
      }
    }
  ],
  "configuration_version": "1"
}